lnauth_django/__init__.py
lnauth_django/apps.py
lnauth_django/django_auth.py
lnauth_django/exceptions.py
lnauth_django/lnauth.py
lnauth_django/migrations/0000_initial.py
lnauth_django/migrations/__init__.py
lnauth_django/models.py
lnauth_django/tests/__init__.py
lnauth_django/tests/conftest.py
lnauth_django/tests/test_django.py
lnauth_django/tests/test_service.py
lnauth_django/urls.py
lnauth_django/views.py
lnauth_django-0.4.1.dist-info/LICENSE
lnauth_django-0.4.1.dist-info/METADATA
lnauth_django-0.4.1.dist-info/WHEEL
lnauth_django-0.4.1.dist-info/RECORD
