Metadata-Version: 2.1
Name: lnauth-django
Version: 0.4.1
Summary: 
Author: zwx00
Author-email: blaz@bolt.observer
Requires-Python: >=3.8,<4.0
Classifier: Programming Language :: Python :: 3
Classifier: Programming Language :: Python :: 3.8
Classifier: Programming Language :: Python :: 3.9
Classifier: Programming Language :: Python :: 3.10
Classifier: Programming Language :: Python :: 3.11
Requires-Dist: bech32 (>=1.2.0,<2.0.0)
Requires-Dist: django (>=3,<4)
Requires-Dist: secp256k1 (>=0.14.0,<0.15.0)
